cocojson/__init__.py
cocojson/convert/__init__.py
cocojson/convert/crowdhuman2coco.py
cocojson/convert/cvatvid2coco.py
cocojson/convert/log2coco.py
cocojson/run/__init__.py
cocojson/run/coco_catify.py
cocojson/run/crowdhuman2coco.py
cocojson/run/cvatvid2coco.py
cocojson/run/filter_cat.py
cocojson/run/ignore_prune.py
cocojson/run/insert_img_meta.py
cocojson/run/log2coco.py
cocojson/run/map_cat.py
cocojson/run/match_imgs.py
cocojson/run/merge.py
cocojson/run/merge_from_file.py
cocojson/run/pred_only.py
cocojson/run/remove_empty.py
cocojson/run/sample.py
cocojson/run/sample_by_class.py
cocojson/run/split.py
cocojson/run/split_by_meta.py
cocojson/run/viz.py
cocojson/tools/__init__.py
cocojson/tools/coco_catify.py
cocojson/tools/count_img_meta.py
cocojson/tools/filter_cat.py
cocojson/tools/ignore_prune.py
cocojson/tools/insert_img_meta.py
cocojson/tools/map_cat.py
cocojson/tools/match_imgs.py
cocojson/tools/merge.py
cocojson/tools/pred_only.py
cocojson/tools/remove_empty.py
cocojson/tools/sample.py
cocojson/tools/split.py
cocojson/tools/split_by_meta.py
cocojson/tools/test.py
cocojson/tools/viz.py
cocojson/utils/__init__.py
cocojson/utils/coco_categories.py
cocojson/utils/common.py
cocojson/utils/draw.py
cocojson-0.1.1.dist-info/LICENSE
cocojson-0.1.1.dist-info/METADATA
cocojson-0.1.1.dist-info/WHEEL
cocojson-0.1.1.dist-info/top_level.txt
cocojson-0.1.1.dist-info/RECORD
