Metadata-Version: 2.1
Name: cocojson
Version: 0.1.1
Summary: Utility functions for manipulating COCO json annotation format
Home-page: https://github.com/levan92/cocojson
Author: levan92
Author-email: lingevan0208@gmail.com
License: UNKNOWN
Platform: UNKNOWN
Classifier: Programming Language :: Python :: 3
Classifier: License :: OSI Approved :: MIT License
Classifier: Operating System :: OS Independent
License-File: LICENSE
Requires-Dist: numpy
Requires-Dist: opencv-python (>=4.5)
Requires-Dist: tqdm
Requires-Dist: Pillow
